{
  "Name": "Nespresso01",
  "Enabled": true,
  "DataPoints": [
    {
      "Name": "sp_test_ptl01",
      "Driver": "mssql",
      "Config": "Server=localhost;Database=QuickFlowDb;User Id=sa;Password=Aguia3220;",
      "Params": [
        {
          "Name": "p1",
          "Mode": "FromOTM",
          "TypeCode": "Int32"
        },
        {
          "Name": "p2",
          "Mode": "FromOTM",
          "TypeCode": "String",
          "Length": 100
        },
        {
          "Name": "p3",
          "Mode": "ToOTM",
          "TypeCode": "String",
          "Length": 100
        }
      ]
    },
    {
      "Name": "sp_test_ptl02",
      "Driver": "mssql",
      "Config": "Server=localhost;Database=QuickFlowDb;User Id=sa;Password=Aguia3220;",
      "Params": [
        {
          "Name": "p1",
          "Mode": "FromOTM",
          "TypeCode": "String",
          "Length": 100
        },
        {
          "Name": "p2",
          "Mode": "ToOTM",
          "TypeCode": "String",
          "Length": 100
        }
      ]
    }
  ],
  "Devices": [
    {
      "Name": "ptl01",
      "Driver": "ptl",
      "Config": "ip=127.0.0.1;port=4660",
      "Tags": [
        {
          "Name": "ptl_ctrl",
          "Address": "ptl_ctrl",
          "Rate": 0,
          "Mode": "ToOTM",
          "TypeCode": "String"
        },
        {
          "Name": "cmd_count",
          "Address": "cmd_count",
          "Rate": 0,
          "Mode": "ToOTM",
          "TypeCode": "Int32"
        },
        {
          "Name": "cmd_rcvd",
          "Address": "cmd_rcvd",
          "Rate": 0,
          "Mode": "ToOTM",
          "TypeCode": "String"
        },
        {
          "Name": "cmd_send",
          "Address": "cmd_send",
          "Rate": 0,
          "Mode": "FromOTM",
          "TypeCode": "String"
        }
      ]
    }
  ],
  "Transactions": [
    {
      "Name": "ptl01_recv",
      "DataPointName": "sp_test_ptl01",
      "DeviceName": "ptl01",
      "TriggerType": "OnTagChange",
      "TriggerTagName": "cmd_count",
      "Binds": [
        {
          "DataPointParam": "p1",
          "DeviceTag": "cmd_count"
        },
        {
          "DataPointParam": "p2",
          "DeviceTag": "cmd_rcvd"
        },
        {
          "DataPointParam": "p3",
          "DeviceTag": "cmd_send"
        }
      ]
    },
    {
      "Name": "ptl01_cycle",
      "DataPointName": "sp_test_ptl02",
      "DeviceName": "ptl01",
      "TriggerType": "OnCycle",
      "TriggerTime": 2000,
      "Binds": [
        {
          "DataPointParam": "p1",
          "DeviceTag": "ptl_ctrl"
        },
        {
          "DataPointParam": "p2",
          "DeviceTag": "cmd_send"
        }
      ]
    }
  ]
}
